MANIFEST.in
Pipfile
Pipfile.lock
setup.py
Terrene.egg-info/PKG-INFO
Terrene.egg-info/SOURCES.txt
Terrene.egg-info/dependency_links.txt
Terrene.egg-info/requires.txt
Terrene.egg-info/top_level.txt
terrene/__init__.py
terrene/auth.py
terrene/contrib.py
terrene/display.py
terrene/model.py
terrene/store.py
terrene/tests.py