Metadata-Version: 1.1
Name: Terrene
Version: 2.0.3
Summary: Terrene's Python SDK
Home-page: https://docs.terrene.co
Author: Terrene
Author-email: developers@terrene.co
License: MIT
Keywords: terrene
Platform: UNKNOWN
Classifier: Development Status :: 4 - Beta
Classifier: Intended Audience :: Developers
Classifier: Topic :: Software Development :: Build Tools
Classifier: License :: OSI Approved :: MIT License
Classifier: Programming Language :: Python :: 3
Classifier: Programming Language :: Python :: 3.3
Classifier: Programming Language :: Python :: 3.4
Classifier: Programming Language :: Python :: 3.5
Classifier: Programming Language :: Python :: 3.6
Classifier: Programming Language :: Python :: 3.7
